my_package/__init__.py
my_package/package.py
hell_package-0.1.0.dist-info/WHEEL
hell_package-0.1.0.dist-info/METADATA
hell_package-0.1.0.dist-info/RECORD
