Metadata-Version: 2.1
Name: hell-package
Version: 0.1.0
Summary: " "
License: MIT
Author: Oussama BATATA
Requires-Python: >=3.9,<4.0
Classifier: License :: OSI Approved :: MIT License
Classifier: Programming Language :: Python :: 3
Classifier: Programming Language :: Python :: 3.10
Classifier: Programming Language :: Python :: 3.9
Requires-Dist: Unidecode (>=1.3.4,<2.0.0)
Requires-Dist: requests (>=2.13.0,<3.0.0)
